thermocepstrum/README.md
thermocepstrum/__init__.py
thermocepstrum/analysis.py
thermocepstrum/heatcurrent.py
thermocepstrum/metadata.json
thermocepstrum/i_o/__init__.py
thermocepstrum/i_o/read_lammps_datafile.py
thermocepstrum/i_o/read_lammps_dump.py
thermocepstrum/i_o/read_lammps_log.py
thermocepstrum/i_o/read_tablefile.py
thermocepstrum/md/__init__.py
thermocepstrum/md/acf.py
thermocepstrum/md/aic.py
thermocepstrum/md/armodel.py
thermocepstrum/md/cepstral.py
thermocepstrum/md/lpfilter.py
thermocepstrum/md/mdsample.py
thermocepstrum/md/tools.py
thermocepstrum/md/units.py
thermocepstrum/utils/__init__.py
thermocepstrum/utils/blockanalysis.py
thermocepstrum/utils/blocks.py
thermocepstrum/utils/loadAfterPlt.py
thermocepstrum/utils/plot_style.mplstyle
thermocepstrum/utils/utils.py
thermocepstrum_gui/README_GUI.md
thermocepstrum_gui/__init__.py
thermocepstrum_gui/main.py
thermocepstrum_gui/assets/__init__.py
thermocepstrum_gui/assets/icon.gif
thermocepstrum_gui/assets/languages.json
thermocepstrum_gui/core/__init__.py
thermocepstrum_gui/core/control_unit.py
thermocepstrum_gui/core/settings.py
thermocepstrum_gui/interfaces/__init__.py
thermocepstrum_gui/interfaces/fileManager.py
thermocepstrum_gui/interfaces/fstarSelector.py
thermocepstrum_gui/interfaces/headerSelector.py
thermocepstrum_gui/interfaces/otherVariables.py
thermocepstrum_gui/interfaces/pstarSelector.py
thermocepstrum_gui/utils/Graph.py
thermocepstrum_gui/utils/__init__.py
thermocepstrum_gui/utils/custom_widgets.py
thermocepstrum_gui/utils/utils.py
thermocepstrum_gui/utils/tk_html_widgets/__init__.py
thermocepstrum_gui/utils/tk_html_widgets/html_parser.py
thermocepstrum-0.3.0.dist-info/LICENSE.txt
thermocepstrum-0.3.0.dist-info/METADATA
thermocepstrum-0.3.0.dist-info/WHEEL
thermocepstrum-0.3.0.dist-info/entry_points.txt
thermocepstrum-0.3.0.dist-info/top_level.txt
thermocepstrum-0.3.0.dist-info/RECORD
