Metadata-Version: 2.1
Name: thermocepstrum
Version: 0.3.0
Summary: Cepstral Data Analysis of current time series for Green-Kubo transport coefficients
Home-page: https://github.com/lorisercole/thermocepstrum
Author: Loris Ercole, Riccardo Bertossa, Sebastiano Bisacchi
Author-email: loris.ercole@epfl.ch
License: GPL 3
Keywords: cepstral data analysis thermal conductivity transport coefficients physics green-kubo
Platform: UNKNOWN
Classifier: Development Status :: 4 - Beta
Classifier: Programming Language :: Python
Classifier: Programming Language :: Python :: 2.7
Classifier: Programming Language :: Python :: 3.5
Classifier: Programming Language :: Python :: 3.6
Classifier: License :: OSI Approved :: GNU General Public License v3 (GPLv3)
Classifier: Operating System :: OS Independent
Classifier: Intended Audience :: Science/Research
Classifier: Intended Audience :: Developers
Classifier: Natural Language :: English
Classifier: Topic :: Scientific/Engineering :: Physics
Classifier: Environment :: Console
Requires-Python: >=2.7, !=3.0.*, !=3.1.*, !=3.2.*, !=3.3.*, <4
Requires-Dist: numpy (>=1.12.0)
Requires-Dist: scipy (>=0.18.1)
Requires-Dist: matplotlib (>=2.2.0)
Requires-Dist: future-fstrings (>=0.1.0)
Requires-Dist: markdown2 (>=2.0.0)
Requires-Dist: pillow (>=5.4.0)
Requires-Dist: uncertainties (>=2.4)
Provides-Extra: notebook
Requires-Dist: jupyter (==1.0.0) ; extra == 'notebook'
Provides-Extra: pre-commit
Requires-Dist: pre-commit (>1.11.0) ; extra == 'pre-commit'
Requires-Dist: yapf (>0.24.0) ; extra == 'pre-commit'
Provides-Extra: testing
Requires-Dist: tox (>=2.0) ; extra == 'testing'
Requires-Dist: pytest (>=4.0) ; extra == 'testing'
